pyGlobServe/__init__.py
pyGlobServe-1.0.0.dist-info/LICENSE
pyGlobServe-1.0.0.dist-info/METADATA
pyGlobServe-1.0.0.dist-info/WHEEL
pyGlobServe-1.0.0.dist-info/top_level.txt
pyGlobServe-1.0.0.dist-info/RECORD
