Metadata-Version: 2.1
Name: pyGlobServe
Version: 1.0.0
Summary: pyGlobServe
Home-page: UNKNOWN
Author: SujithSouryaYedida
Author-email: sujithsourya.yedida@gmail.com
License: UNKNOWN
Keywords: server,python,tcp room,chat,SujithSouryaYedida,py,chat room,localhost,hosted,server room
Platform: UNKNOWN
Classifier: Development Status :: 1 - Planning
Classifier: Intended Audience :: Developers
Classifier: Programming Language :: Python :: 3
Classifier: Operating System :: Unix
Classifier: Operating System :: MacOS :: MacOS X
Classifier: Operating System :: Microsoft :: Windows
License-File: LICENSE
Requires-Dist: pyfiglet
Requires-Dist: tqdm
Requires-Dist: colorama
